MANIFEST.in
README.rst
setup.cfg
setup.py
doc/Makefile
doc/array.rst
doc/conf.py
doc/connection.rst
doc/discretization.rst
doc/index.rst
doc/interop.rst
doc/mesh.rst
doc/misc.rst
doc/images/Makefile
doc/images/facial-adjacency-group.png
doc/images/facial-adjacency-group.tex
doc/images/nodes-vertices.png
doc/images/nodes-vertices.tex
doc/images/torus.png
examples/from_firedrake.py
examples/mesh-to-tikz.py
examples/moving-geometry.py
examples/multiple-meshes.py
examples/plot-connectivity.py
examples/simple-dg.py
examples/to_firedrake.py
meshmode/__init__.py
meshmode/array_context.py
meshmode/distributed.py
meshmode/dof_array.py
meshmode/version.py
meshmode.egg-info/PKG-INFO
meshmode.egg-info/SOURCES.txt
meshmode.egg-info/dependency_links.txt
meshmode.egg-info/requires.txt
meshmode.egg-info/top_level.txt
meshmode/discretization/__init__.py
meshmode/discretization/poly_element.py
meshmode/discretization/visualization.py
meshmode/discretization/connection/__init__.py
meshmode/discretization/connection/chained.py
meshmode/discretization/connection/direct.py
meshmode/discretization/connection/face.py
meshmode/discretization/connection/modal.py
meshmode/discretization/connection/opposite_face.py
meshmode/discretization/connection/projection.py
meshmode/discretization/connection/refinement.py
meshmode/discretization/connection/same_mesh.py
meshmode/interop/__init__.py
meshmode/interop/nodal_dg.py
meshmode/interop/firedrake/__init__.py
meshmode/interop/firedrake/connection.py
meshmode/interop/firedrake/mesh.py
meshmode/interop/firedrake/reference_cell.py
meshmode/mesh/__init__.py
meshmode/mesh/generation.py
meshmode/mesh/io.py
meshmode/mesh/processing.py
meshmode/mesh/tools.py
meshmode/mesh/visualization.py
meshmode/mesh/refinement/__init__.py
meshmode/mesh/refinement/no_adjacency.py
meshmode/mesh/refinement/tesselate.py
meshmode/mesh/refinement/utils.py
test/annulus.msh
test/ball-radius-1.step
test/blob-2d.step
test/blob2d-order1-h4e-2.msh
test/blob2d-order1-h6e-2.msh
test/blob2d-order1-h8e-2.msh
test/blob2d-order4-h4e-2.msh
test/blob2d-order4-h6e-2.msh
test/blob2d-order4-h8e-2.msh
test/circle.step
test/cube.step
